caped_ai_sentinal/__init__.py
caped_ai_sentinal/_version.py
caped_ai_sentinal/caped.yaml
caped_ai_sentinal/SentinalFunctions/__init__.py
caped_ai_sentinal/SentinalFunctions/model_prediction.py
caped_ai_sentinal/SentinalFunctions/model_training.py
caped_ai_sentinal/_tests/__init__.py
caped_ai_sentinal-0.0.1.dist-info/LICENSE
caped_ai_sentinal-0.0.1.dist-info/METADATA
caped_ai_sentinal-0.0.1.dist-info/WHEEL
caped_ai_sentinal-0.0.1.dist-info/entry_points.txt
caped_ai_sentinal-0.0.1.dist-info/top_level.txt
caped_ai_sentinal-0.0.1.dist-info/RECORD
