Metadata-Version: 2.1
Name: caped-ai-sentinal
Version: 0.0.1
Summary: A wrapper function package to call Sentinal library for training
Home-page: https://github.com/Kapoorlabs-CAPED/caped-ai-sentinal
Author: Varun Kapoor
Author-email: randomaccessiblekapoor@gmail.com
License: BSD-3-Clause
Project-URL: Bug Tracker, https://github.com/Kapoorlabs-CAPED/caped-ai-sentinal/issues
Project-URL: Documentation, https://github.com/Kapoorlabs-CAPED/caped-ai-sentinal#README.md
Project-URL: Source Code, https://github.com/Kapoorlabs-CAPED/caped-ai-sentinal
Project-URL: User Support, https://github.com/Kapoorlabs-CAPED/caped-ai-sentinal/issues
Classifier: Development Status :: 5 - Production/Stable
Classifier: Intended Audience :: Developers
Classifier: License :: OSI Approved :: BSD License
Classifier: Operating System :: OS Independent
Classifier: Programming Language :: Python
Classifier: Programming Language :: Python :: 3
Classifier: Programming Language :: Python :: 3 :: Only
Classifier: Programming Language :: Python :: 3.8
Classifier: Programming Language :: Python :: 3.9
Classifier: Programming Language :: Python :: 3.10
Classifier: Topic :: Scientific/Engineering :: Image Processing
Requires-Python: >=3.8
License-File: LICENSE
Requires-Dist: caped-ai
Provides-Extra: testing
Requires-Dist: tox ; extra == 'testing'
Requires-Dist: pytest ; extra == 'testing'
Requires-Dist: pytest-cov ; extra == 'testing'
